{
  "entry": [
    {
      "entryType": "mm",
      "code": "441313008",
      "display": "Indolent multiple myeloma (disorder)"
    },
    {
      "entryType": "mm",
      "code": "440422002",
      "display": "Asymptomatic multiple myeloma (disorder)"
    },
    {
      "entryType": "mm",
      "code": "425657001",
      "display": "Osteosclerotic myeloma (disorder)"
    },
    {
      "entryType": "mm",
      "code": "415110002",
      "display": "Plasma cell myeloma/plasmacytoma (disorder)"
    },
    {
      "entryType": "mm",
      "code": "414553000",
      "display": "Kappa light chain myeloma (disorder)"
    },
    {
      "entryType": "mm",
      "code": "313427003",
      "display": "Lambda light chain myeloma (disorder)"
    },
    {
      "entryType": "mm",
      "code": "285422003",
      "display": "Immunoglobulin D myeloma (disorder)"
    },
    {
      "entryType": "mm",
      "code": "285421005",
      "display": "Immunoglobulin G myeloma (disorder)"
    },
    {
      "entryType": "mm",
      "code": "285420006",
      "display": "Immunoglobulin A myeloma (disorder)"
    },
    {
      "entryType": "mm",
      "code": "277580004",
      "display": "Non-secretory myeloma (disorder)"
    },
    {
      "entryType": "mm",
      "code": "277579002",
      "display": "Light chain myeloma (disorder)"
    },
    {
      "entryType": "mm",
      "code": "109989006",
      "display": "Multiple myeloma (disorder)"
    },
    {
      "entryType": "mm",
      "code": "95210003",
      "display": "Plasma cell leukemia, disease (disorder)"
    },
    {
      "entryType": "mm",
      "code": "413587002",
      "display": "Smoldering myeloma (disorder)"
    }
  ]
}
